{
  "schema_version": "1.0",
  "generated_at": "2026-04-24T08:23:06+02:00",
  "source": "open-meteo.com (Kijkduin strand)",
  "location": {"lat":52.06,"lon":4.196,"naam":"Kijkduin strand (Zandmotorpad)"},
  "forecast": [
    {"ds":"2026-04-24","temp_mean":9.6,"temp_max":11.4,"sunshine_hrs":13.4,"rainfall_mm":0,"wind_mean_ms":5.1},
    {"ds":"2026-04-25","temp_mean":9.1,"temp_max":11.8,"sunshine_hrs":13.3,"rainfall_mm":0,"wind_mean_ms":2.9},
    {"ds":"2026-04-26","temp_mean":9.7,"temp_max":11.7,"sunshine_hrs":13.9,"rainfall_mm":0,"wind_mean_ms":4.1},
    {"ds":"2026-04-27","temp_mean":9.7,"temp_max":13.4,"sunshine_hrs":12.2,"rainfall_mm":2.1,"wind_mean_ms":2.8},
    {"ds":"2026-04-28","temp_mean":10.3,"temp_max":14.2,"sunshine_hrs":14.1,"rainfall_mm":0.9,"wind_mean_ms":5.4},
    {"ds":"2026-04-29","temp_mean":10.8,"temp_max":14.9,"sunshine_hrs":14.6,"rainfall_mm":0,"wind_mean_ms":5.2},
    {"ds":"2026-04-30","temp_mean":10.3,"temp_max":13.7,"sunshine_hrs":14.6,"rainfall_mm":0,"wind_mean_ms":5.5},
    {"ds":"2026-05-01","temp_mean":11,"temp_max":15.6,"sunshine_hrs":14.7,"rainfall_mm":0,"wind_mean_ms":4.3},
    {"ds":"2026-05-02","temp_mean":10.8,"temp_max":15.2,"sunshine_hrs":14.7,"rainfall_mm":0,"wind_mean_ms":3.8},
    {"ds":"2026-05-03","temp_mean":9.8,"temp_max":11.9,"sunshine_hrs":14.7,"rainfall_mm":0,"wind_mean_ms":5.1},
    {"ds":"2026-05-04","temp_mean":9.1,"temp_max":11.1,"sunshine_hrs":10.6,"rainfall_mm":0,"wind_mean_ms":4.2},
    {"ds":"2026-05-05","temp_mean":8.4,"temp_max":11.4,"sunshine_hrs":14.2,"rainfall_mm":0,"wind_mean_ms":3.8},
    {"ds":"2026-05-06","temp_mean":8.7,"temp_max":12.1,"sunshine_hrs":14.4,"rainfall_mm":0,"wind_mean_ms":5.2},
    {"ds":"2026-05-07","temp_mean":7.2,"temp_max":7.9,"sunshine_hrs":0,"rainfall_mm":4.8,"wind_mean_ms":5.3}
  ]
}
